odoo8_addon_sale_layout_multi_company-8.0.1.0.0-py2.7-nspkg.pth
odoo8_addon_sale_layout_multi_company-8.0.1.0.0.dist-info/DESCRIPTION.rst
odoo8_addon_sale_layout_multi_company-8.0.1.0.0.dist-info/METADATA
odoo8_addon_sale_layout_multi_company-8.0.1.0.0.dist-info/RECORD
odoo8_addon_sale_layout_multi_company-8.0.1.0.0.dist-info/WHEEL
odoo8_addon_sale_layout_multi_company-8.0.1.0.0.dist-info/metadata.json
odoo8_addon_sale_layout_multi_company-8.0.1.0.0.dist-info/namespace_packages.txt
odoo8_addon_sale_layout_multi_company-8.0.1.0.0.dist-info/top_level.txt
odoo_addons/sale_layout_multi_company/README.rst
odoo_addons/sale_layout_multi_company/__init__.py
odoo_addons/sale_layout_multi_company/__openerp__.py
odoo_addons/sale_layout_multi_company/models/__init__.py
odoo_addons/sale_layout_multi_company/models/sale_layout.py
odoo_addons/sale_layout_multi_company/security/record_rules.xml
odoo_addons/sale_layout_multi_company/static/description/icon.png
odoo_addons/sale_layout_multi_company/views/sale_layout_view.xml
